SaranyaNarayansetti/__init__.py
SaranyaNarayansetti/saruoperations.py
SaranyaNarayansetti-0.0.1.dist-info/METADATA
SaranyaNarayansetti-0.0.1.dist-info/WHEEL
SaranyaNarayansetti-0.0.1.dist-info/top_level.txt
SaranyaNarayansetti-0.0.1.dist-info/RECORD
