Metadata-Version: 2.1
Name: SaranyaNarayansetti
Version: 0.0.1
Summary: Saranya Narayansetti Package
Author: Sai Praneeth Renduchinthala
Author-email: praneeth.renduchinthala210@gmail.com
Keywords: SaranyaNarayansetti,SaranyaNarayansetti package
Classifier: Development Status :: 3 - Alpha
Classifier: Intended Audience :: Education
Classifier: Programming Language :: Python :: 2
Classifier: Programming Language :: Python :: 3
Classifier: Operating System :: MacOS :: MacOS X
Classifier: Operating System :: Microsoft :: Windows
